trackj/__init__.py
trackj/tracker.py
trackj-0.1.0.dist-info/METADATA
trackj-0.1.0.dist-info/WHEEL
trackj-0.1.0.dist-info/RECORD
