Metadata-Version: 2.1
Name: trackj
Version: 0.1.0
Summary: A simple package for determining shipping carriers and generating tracking URLs.
Home-page: https://github.com/earonesty/trackj
License: MIT
Author: Erik Aronesty
Author-email: erik@q32.com
Requires-Python: >=3.8,<4.0
Classifier: License :: OSI Approved :: MIT License
Classifier: Programming Language :: Python :: 3
Classifier: Programming Language :: Python :: 3.8
Classifier: Programming Language :: Python :: 3.9
Classifier: Programming Language :: Python :: 3.10
Classifier: Programming Language :: Python :: 3.11
Classifier: Programming Language :: Python :: 3.12
